<?xml version="1.0" encoding="utf-8"?>
<odoo noupdate="1">
    <record id="trailer_53_dry_van" model="cargo.architect.trailer.preset">
        <field name="name">53 ft Dry Van - Interior Approx. 636 x 98 x 110 in</field>
        <field name="sequence">1</field>
        <field name="length_in">636</field>
        <field name="width_in">98</field>
        <field name="height_in">110</field>
        <field name="max_payload_lbs">45000</field>
        <field name="fifth_wheel_position_in">36</field>
        <field name="trailer_axle_position_in">516</field>
    </record>
    <record id="trailer_48_dry_van" model="cargo.architect.trailer.preset">
        <field name="name">48 ft Dry Van - Interior Approx. 576 x 98 x 110 in</field>
        <field name="sequence">2</field>
        <field name="length_in">576</field>
        <field name="width_in">98</field>
        <field name="height_in">110</field>
        <field name="max_payload_lbs">44000</field>
        <field name="fifth_wheel_position_in">36</field>
        <field name="trailer_axle_position_in">456</field>
    </record>
    <record id="preset_standard_pallet" model="cargo.architect.product.preset">
        <field name="name">Standard 48 x 40 Pallet</field>
        <field name="length_in">48</field>
        <field name="width_in">40</field>
        <field name="height_in">48</field>
        <field name="weight_lbs">0</field>
        <field name="allow_rotate">1</field>
    </record>

    <!-- v2.0.14: Report option defaults are handled by res.config.settings
         config_parameter fields and safe set_param calls when users save settings.
         Do NOT create ir.config_parameter rows here; direct XML records can
         duplicate existing keys during upgrades and abort module loading. -->

</odoo>
